{
  "price": 73062.41,
  "ema20": 69355.70791021922,
  "ema200": 80411.49876661727,
  "ema4H50": 69961.89012598367,
  "ema10": 69779.01840484419,
  "ema30": 70152.63285322506,
  "fundingRate": 0.00004263,
  "fundingSentiment": "neutral",
  "regime": "BEAR",
  "above20": true,
  "above4H50": true,
  "baseAction": "EXIT",
  "action": "EXIT",
  "direction": "cash",
  "confirmed": true,
  "confirmations": [],
  "warnings": [],
  "stopPrice": null,
  "leverage": 3,
  "ema1030Signal": "BEARISH",
  "ema1030Action": "FLAT (cash)",
  "timestamp": "2026-03-13T13:22:21.018Z"
}