{
  "price": 72225.99,
  "ema20": 69276.6183864097,
  "ema200": 80395.05441018163,
  "ema4H50": 69823.3386858068,
  "ema10": 69628.0293139351,
  "ema30": 70099.05607903152,
  "fundingRate": 0.00004263,
  "fundingSentiment": "neutral",
  "regime": "BEAR",
  "above20": true,
  "above4H50": true,
  "baseAction": "EXIT",
  "action": "EXIT",
  "direction": "cash",
  "confirmed": true,
  "confirmations": [],
  "warnings": [],
  "stopPrice": null,
  "leverage": 3,
  "ema1030Signal": "BEARISH",
  "ema1030Action": "FLAT (cash)",
  "timestamp": "2026-03-13T10:02:56.380Z"
}