{
  "price": 71492,
  "ema20": 69206.74791021922,
  "ema200": 80380.52688542915,
  "ema4H50": 69988.79893924737,
  "ema10": 69494.640223026,
  "ema30": 70051.72446612829,
  "fundingRate": -0.00000638,
  "fundingSentiment": "neutral",
  "regime": "BEAR",
  "above20": true,
  "above4H50": true,
  "baseAction": "EXIT",
  "action": "EXIT",
  "direction": "cash",
  "confirmed": true,
  "confirmations": [],
  "warnings": [],
  "stopPrice": null,
  "leverage": 3,
  "ema1030Signal": "BEARISH",
  "ema1030Action": "FLAT (cash)",
  "timestamp": "2026-03-13T16:31:17.424Z"
}