{
  "price": 71177.04,
  "ema20": 69176.75267212398,
  "ema200": 80374.2902517658,
  "ema4H50": 69622.54320263074,
  "ema10": 69437.37658666237,
  "ema30": 70031.40511128958,
  "fundingRate": -0.00002789,
  "fundingSentiment": "neutral",
  "regime": "BEAR",
  "above20": true,
  "above4H50": true,
  "baseAction": "EXIT",
  "action": "EXIT",
  "direction": "cash",
  "confirmed": true,
  "confirmations": [],
  "warnings": [],
  "stopPrice": null,
  "leverage": 3,
  "ema1030Signal": "BEARISH",
  "ema1030Action": "FLAT (cash)",
  "timestamp": "2026-03-13T03:00:34.468Z"
}